{
  "doi": "10.1145/1978942.1978989",
  "title": "Mining behavioral economics to design persuasive technology for healthy choices",
  "published": "2011-05-07",
  "proctitle": "CHI '11: Proceedings of the SIGCHI Conference on Human Factors in Computing Systems",
  "pages": "325-334",
  "year": 2011,
  "badges": [],
  "abstract": "Influence through information and feedback has been one of the main approaches of persuasive technology. We propose another approach based on behavioral economics research on decision-making. This approach involves designing the presentation and timing of choices to encourage people to make self-beneficial decisions. We applied three behavioral economics persuasion techniques - the default option strategy, the planning strategy, and the asymmetric choice strategy - to promote healthy snacking in the workplace. We tested the strategies in three experimental case studies using a human snack deliverer, a robot, and a snack ordering website. The default and the planning strategies were effective, but they worked differently depending on whether the participants had healthy dietary lifestyles or not. We discuss designs for persuasive technologies that apply behavioral economics.",
  "authors": [
    {
      "name": "Min Kyung Lee",
      "institution": "Carnegie Mellon University, Pittsburgh, Pennsylvania, USA",
      "img": "/do/10.1145/contrib-81414592368/rel-imgonly/mklee.png",
      "acmid": "81414592368",
      "orcid": "0000-0002-2696-6546"
    },
    {
      "name": "Sara Kiesler",
      "institution": "Carnegie Mellon University, Pittsburgh, Pennsylvania, USA",
      "img": "/do/10.1145/contrib-81100476487/rel-imgonly/kiesler2001.jpg",
      "acmid": "81100476487",
      "orcid": "missing"
    },
    {
      "name": "Jodi Forlizzi",
      "institution": "Carnegie Mellon University, Pittsburgh, Pennsylvania, USA",
      "img": "/pb-assets/icons/DOs/default-profile-1543932446943.svg",
      "acmid": "81100492013",
      "orcid": "missing"
    }
  ],
  "references": [
    {
      "text": "Berdichevsky, D. & Neuenschwander, E. (1999). Toward an ethics of persuasive technology. Communications of the ACM, 42 (5).  ",
      "doi": "10.1145/301353.301410"
    },
    {
      "text": "Brown, B., Chetty, M., Grimes, A., & Harmon, E., (2006). Reflecting on health: A system for students to monitor diet and exercise. In Proceedings of CHI'06, 1807--1812.  ",
      "doi": "10.1145/1125451.1125794"
    },
    {
      "text": "Camerer, C., Issacharoff, S., Samuel, C., & Loewenstein, G. (2003). Regulation for Conservatives: Behavioral Economics and the Case for \"Asymmetric Paternalism.\" University of Pennsylvania Law Review, 151, 1211--1254.",
      "doi": ""
    },
    {
      "text": "Card, S., Moran, T., and Newell, A. (1986). The model human processor: An engineering model of human performance. In Handbook of Perception and Human Performance. John Wiley and Sons, 1--35.",
      "doi": ""
    },
    {
      "text": "Chi, P.-Y., Chen, J.-H., Chu, H.-H. & Chen, B.-Y. (2007). Enabling nutrition-aware cooking in a smart kitchen. In Proceedings of CHI'07, 2333--2338.  ",
      "doi": "10.1145/1240866.1241003"
    },
    {
      "text": "Dey, A. K. (2001). Understanding and using context. Journal of Personal and Ubiquitous Computing, 4--7.  ",
      "doi": "10.1007/s007790170019"
    },
    {
      "text": "Downs, J., Loewenstein, G., & Wisdom, J. (2009) Strategies for promoting healthier food choices. American Economic Review, 99, 159--164.",
      "doi": ""
    },
    {
      "text": "Feldman, M. S., & March, J. G. (1981). Information in organizations as signal and symbol. Administrative Science Quarterly, 26(2), 171--186.",
      "doi": ""
    },
    {
      "text": "Fogg, B. J. (2002). Persuasive technology: Using computers to change what we think and do. Morgan Kaufmann. ",
      "doi": "10.5555/640634"
    },
    {
      "text": "Friedman, B. (1997). Human values and the design of computer technology. Cambridge University Press. ",
      "doi": "10.5555/278213"
    },
    {
      "text": "Grimes, A & Grinter, R. E. (2007). Designing persuasion: Health technology for low-income African American communities. PERSUASIVE 2007, 24--35. ",
      "doi": "10.5555/1780402.1780407"
    },
    {
      "text": "Huber, J., Payne, J. W., & Puto, C. (1982). Adding asymmetrically dominated alternatives: Violations of regularity and the similarity hypothesis. Journal of Consumer Research, 9, 90--98.",
      "doi": ""
    },
    {
      "text": "Intuitive Automata, http://intuitiveautomata.com.",
      "doi": ""
    },
    {
      "text": "Kahneman, D., Knetsch, J., & Thaler, R. (1991). Anomalies: The endowment effect, loss aversion, and status quo bias. Journal of Economic Perspectives, 5, 1, 193--206.",
      "doi": ""
    },
    {
      "text": "Kahneman, D. (2003). Maps of bounded rationality: Psychology for behavioral economics. American Economic Review, 1449--1475.",
      "doi": ""
    },
    {
      "text": "Kahn U., & Dhar, R. (2007). Where there is a way, is there a will? The effect of future choices on self-control. Journal of Experimental Psychology, 277--288.",
      "doi": ""
    },
    {
      "text": "Lee, M. K., Forlizzi, J., Rybski, P. E., Crabbe, F., Chung, W., Finkle, J., Glaser, E., & Kiesler, S. (2009). The Snackbot: Documenting the design of a robot for long-term Human-Robot Interaction. In Proceedings of HRI'09, 7--14.  ",
      "doi": "10.1145/1514095.1514100"
    },
    {
      "text": "Loewenstein, G., Brennan, T. and Volpp, K. G. (2007). Protecting people from themselves: using decision errors to help people improve their health. Journal of the American Medical Association. 298(20), 2415--2417.",
      "doi": ""
    },
    {
      "text": "Loewenstein, G. (1996). Out of control: Visceral influences on behavior. Organizational Behavior and Human Decision Processes, 65, 272--292.",
      "doi": ""
    },
    {
      "text": "Loewenstein, G., O'Donoghue, T. M., & Rabin, M. (2003). Projection bias in predicting future utility. Quarterly Journal of Economics, 118, 1209--1248.",
      "doi": ""
    },
    {
      "text": "Mankoff, J., Hsieh, G., Hung, H. C., Lee, & S., Nitao, E. (2002). Using low-cost sensing to support nutritional awareness. In Proceedings of Ubicomp'02, 371--378. ",
      "doi": "10.5555/647988.761044"
    },
    {
      "text": "McCrory, M. A., Fuss, P. J., McCallum, J. E., Yao, M., Vinken, A. G., & Hays, N. P. (1999). Dietary variety within food groups: Association with energy intake and body fatness in men and women. The American Journal of Clinical Nutrition, 69, 440--447.",
      "doi": ""
    },
    {
      "text": "Mowen, J. C. (1999). The 3M model of motivation and personality: Theory and empirical applications to consumer behavior. Springer.",
      "doi": ""
    },
    {
      "text": "Norman, D. A. (1988). The design of everyday things. Basic Books.",
      "doi": ""
    },
    {
      "text": "Polivy, J. (1998). The effects of behavioral inhibition: Integrating internal cues, cognition, behavior, and affect. Psychological Inquiry, 9, 181--204.",
      "doi": ""
    },
    {
      "text": "Read, D., & van Leeuwen, B. (1998). Predicting hunger: The effects of appetite and delay on choice. Organizational Behavior and Human Decision Processes, 76(2), 189--205.",
      "doi": ""
    },
    {
      "text": "Samuelson, W. & Zeckhauser, R. (1988). Status quo bias in decision making. Journal of Risk and Uncertainty, 1, 7--59.",
      "doi": ""
    },
    {
      "text": "Seymour, J. D., Yaroch, A. L., Serdula, M., Blanck, H. M., & Khan, L. K. (2004). Impact of nutrition environmental interventions on point-of-purchase behavior in adults: A review. Preventative Medicine, 39, 108--136.",
      "doi": ""
    },
    {
      "text": "Shneiderman, B. and Plaisant, C. (2009). Designing the user interface. 5th edition. Addison Wesley. ",
      "doi": "10.5555/1593001"
    },
    {
      "text": "Thaler, R. H. & Benartzi, S. (2004). Save more tomorrow: Using behavioral economics to increase employee saving. Journal of Political Economy, 112, 164--187.",
      "doi": ""
    },
    {
      "text": "Thaler, R. H., & Sunstein, C. R. (2008). Nudge: Improving decisions about health, wealth, and happiness. New Haven: Yale University Press.",
      "doi": ""
    },
    {
      "text": "Thomas, L. C., & Wickens, C. D. (2001). Visual displays and cognitive tunneling: Frames of reference effects on spatial judgments and change detection. In Proceedings of Human Factors and Ergonomics Society Annual Meeting, 336--340.",
      "doi": ""
    },
    {
      "text": "Wansink, B. & Chandon, P. (2006). Can \"low-fat\" nutrition labels lead to obesity? Journal of Marketing Research, 43, 605--661.",
      "doi": ""
    },
    {
      "text": "Wilcox, K., Vallen, B., Block, L., & Fitzsimons, G. J. (2009). Vicarious goal fulfillment: When the mere presence of a healthy option leads to an ironically indulgent decision. Journal of Consumer Research, 36, 3, 380--393.",
      "doi": ""
    }
  ]
}