{
  "doi": "10.1145/1978942.1979127",
  "title": "Augmenting web pages and search results to support credibility assessment",
  "published": "2011-05-07",
  "proctitle": "CHI '11: Proceedings of the SIGCHI Conference on Human Factors in Computing Systems",
  "pages": "1245-1254",
  "year": 2011,
  "badges": [],
  "abstract": "The presence (and, sometimes, prominence) of incorrect and misleading content on the Web can have serious consequences for people who increasingly rely on the internet as their information source for topics such as health, politics, and financial advice. In this paper, we identify and collect several page features (such as popularity among specialized user groups) that are currently difficult or impossible for end users to assess, yet provide valuable signals regarding credibility. We then present visualizations designed to augment search results and Web pages with the most promising of these features. Our lab evaluation finds that our augmented search results are particularly effective at increasing the accuracy of users'\" credibility assessments, highlighting the potential of data aggregation and simple interventions to help people make more informed decisions as they search for information online.",
  "authors": [
    {
      "name": "Julia Schwarz",
      "institution": "Carnegie Mellon University & Microsoft Research, Pittsburgh, Pennsylvania, USA",
      "img": "/pb-assets/icons/DOs/default-profile-1543932446943.svg",
      "acmid": "81416594005",
      "orcid": "missing"
    },
    {
      "name": "Meredith Morris",
      "institution": "Microsoft Research, Redmond, Washington, USA",
      "img": "/do/10.1145/contrib-81452607037/rel-imgonly/merriesquare.jpg",
      "acmid": "81452607037",
      "orcid": "0000-0003-1436-9223"
    }
  ],
  "references": [
    {
      "text": "Banko, M., Cafarella, M.J., Soderland, S., Broadhead, M., and Etzioni, O. Open information extraction from the Web. IJCAI 2007, 2670--2676. ",
      "doi": "10.5555/1625275.1625705"
    },
    {
      "text": "Bhavnani, S. Domain-Specific Search Strategies for the Effective Retrieval of Healthcare and Shopping Infor-mation. CHI 2002 Extended Abstracts, 610--611.  ",
      "doi": "10.1145/506443.506508"
    },
    {
      "text": "Brin, S. and Page, L. The anatomy of a large-scale hy-pertextual Web search engine. ISDN 1998, 107--117.  ",
      "doi": "10.1016/S0169-7552%2898%2900110-X"
    },
    {
      "text": "Cavarlee, J. and Liu, L. Countering Web spam with credibility-based link analysis. PODC 2007, 157--166.  ",
      "doi": "10.1145/1281100.1281124"
    },
    {
      "text": "Chi, E., Pirolli, P., Chen, K., and Pitkow, J. Using in-formation scent to model user information needs and ac-tions and the Web. CHI 2001, 490--497.  ",
      "doi": "10.1145/365024.365325"
    },
    {
      "text": "Cutrell, E. and Guan,Z. What are you looking for? An eye-tracking study of information usage in Web search. CHI 2007, 407--416.  ",
      "doi": "10.1145/1240624.1240690"
    },
    {
      "text": "Dignan, L. Gartner Puts Phishing Tab at $3.2 Billion. ZDNet. December 17, 2007.",
      "doi": ""
    },
    {
      "text": "Ennals, R. Byler, D., Agosta, J.M. and Rosario, B. What is Disputed on the Web? WICOW 2010, 67--74.  ",
      "doi": "10.1145/1772938.1772952"
    },
    {
      "text": "Fallows, D. Search Engine Users. Pew Internet and American Life Project, 2005.",
      "doi": ""
    },
    {
      "text": "Ferebee, S. An examination of the influence of in-volvement level of Web site users on the perceived cred-ibility of Web sites. PERSUASIVE 2007, 176--186. ",
      "doi": "10.5555/1780402.1780433"
    },
    {
      "text": "Fogg, B.J. Marshall, Laraki, O., Osipovich, A., Varma, C. Fang, N., Paul, J., Rangekar, A., Shon, J., Swani, P., and Treinen, M. What makes Web sites credible?: A re-port on a large quantitative study. CHI 2001, 61--68.  ",
      "doi": "10.1145/365024.365037"
    },
    {
      "text": "Fogg, B.J. Persuasive Technology: Using Computers to Change What We Think and Do. Morgan Kaufmann, 2002. ",
      "doi": "10.5555/640634"
    },
    {
      "text": "Fogg, B. J. Prominence-interpretation theory: explaining how people assess credibility online. CHI 2003 Extend-ed Abstracts, 722--723.  ",
      "doi": "10.1145/765891.765951"
    },
    {
      "text": "Fogg, B.J., Soohoo, C., Danielson, D.R., Marable, L., Stanford, J., and Tauber, E.R. How do users evaluate the credibility of Web sites?: A study with over 2,500 par-ticipants. DUX 2003, 1--15.  ",
      "doi": "10.1145/997078.997097"
    },
    {
      "text": "Gamon, M., Basu, S., Belenko, D., Fisher, D., Hurst, M., and Konig, A.C. BLEWS: Using Blogs to Provide Context for News Articles. ICWSM 2008.",
      "doi": ""
    },
    {
      "text": "Gyongyi, Z., Molina, H.G., and Pederson, J. Combating Web spam with TrustRank. VLDB 2004, 576--587. ",
      "doi": "10.5555/1316689.1316740"
    },
    {
      "text": "Hargittai, E., Fullerton, F., Menchen-Trevino, E. and Thomas, D. Trust online: young adults' evaluation of Web content. International Journal of Communications, 2010.",
      "doi": ""
    },
    {
      "text": "Hilligoss, B. and Rieh, S.Y., Developing a unifying framework of credibility assessment: construct, heuristics, and interaction in context. Information Processing and Management, 44(4), 2008, 1467--1484.  ",
      "doi": "10.1016/j.ipm.2007.10.001"
    },
    {
      "text": "Ivory, M. and Hearst, M. Statistical profiles of highly-rated Web sites. CHI 2002, 367--374.  ",
      "doi": "10.1145/503376.503442"
    },
    {
      "text": "Joachims, T., Granka, L., Pan, B., Hembrooke, H., and Gay, G. Accurately interpreting clickthrough data as implicit feedback. SIGIR 2005, 154--161.  ",
      "doi": "10.1145/1076034.1076063"
    },
    {
      "text": "Jenkins, H. Confronting the Challenges of Participatory Culture: Media Education for the 21st Century. 2006.",
      "doi": ""
    },
    {
      "text": "Kapoun, J. Teaching Undergrads WEB Evaluation: A Guide for Library Instruction. C&RL News, July/August 1998, 522--523.",
      "doi": ""
    },
    {
      "text": "Kittur, A., Suh, B. and Chi, E. Can you ever trust a wiki?: Impacting perceived trustworthiness in Wikipe-dia. CSCW 2008, 477--480.  ",
      "doi": "10.1145/1460563.1460639"
    },
    {
      "text": "Lazar, J., Meiselwitz, G., and Feng, J. Understanding Web Credibility: A Synthesis of the Research Literature. Foundations and Trends in HCI, 1(2), 2007.  ",
      "doi": "10.1561/1100000007"
    },
    {
      "text": "Leu, D.J. and Zawilinski, L. The New Literacies of Online Reading Comprehension. New England Reading Association Journal, 43(1), 2007, 1--7.",
      "doi": ""
    },
    {
      "text": "Lohr, S. This Boring Headline is Written for Google. The New York Times, April 9, 2006.",
      "doi": ""
    },
    {
      "text": "McKnight, D. and Kacmar, C. Factors and effects of information credibility. ICEC 2007, 423--432.  ",
      "doi": "10.1145/1282100.1282180"
    },
    {
      "text": "Metzger, M. J. Making sense of credibility on the Web: Models for evaluating online information and recom-mendations for future research. Journal of the American Society for Information Science and Technology, 58(13), 2007, 2078--2091.  ",
      "doi": "10.5555/1315930.1315940"
    },
    {
      "text": "Pew Research. Growing Number of Americans Say Obama is a Muslim. August 18, 2010.",
      "doi": ""
    },
    {
      "text": "Schneiderman, B. Designing trust into online experienc-es. CACM, 43(12), 2000, 57--59.  ",
      "doi": "10.1145/355112.355124"
    },
    {
      "text": "White, R., Dumais, S., and Teevan, J. Characterizing the influence of domain expertise on Web search behavior. WSDM 2009, 132--141.  ",
      "doi": "10.1145/1498759.1498819"
    },
    {
      "text": "White, R. and Morris, D. Investigating the querying and browsing behavior of advanced search engine users. SIGIR 2007, 255--262.  ",
      "doi": "10.1145/1277741.1277787"
    },
    {
      "text": "Wu, M., Miller, R., and Garfinkel, S. Do security toolbars actually prevent phishing attacks? CHI 2006.  ",
      "doi": "10.1145/1124772.1124863"
    }
  ]
}